oxarchive/__init__.py
oxarchive/client.py
oxarchive/exchanges.py
oxarchive/http.py
oxarchive/types.py
oxarchive/websocket.py
oxarchive/resources/__init__.py
oxarchive/resources/candles.py
oxarchive/resources/funding.py
oxarchive/resources/instruments.py
oxarchive/resources/liquidations.py
oxarchive/resources/openinterest.py
oxarchive/resources/orderbook.py
oxarchive/resources/trades.py
oxarchive-0.5.4.dist-info/METADATA
oxarchive-0.5.4.dist-info/WHEEL
oxarchive-0.5.4.dist-info/RECORD
