Metadata-Version: 2.4
Name: oxarchive
Version: 0.5.4
Summary: Official Python SDK for 0xarchive - Hyperliquid Historical Data API
Project-URL: Homepage, https://0xarchive.io
Project-URL: Documentation, https://0xarchive.io/docs/sdks
Project-URL: Repository, https://github.com/0xarchiveIO/sdk-python
Project-URL: Issues, https://github.com/0xarchiveIO/sdk-python/issues
Author-email: 0xarchive <support@0xarchive.io>
License-Expression: MIT
Keywords: 0xarchive,api,historical-data,hyperliquid,orderbook,sdk,trading
Classifier: Development Status :: 4 - Beta
Classifier: Intended Audience :: Developers
Classifier: License :: OSI Approved :: MIT License
Classifier: Operating System :: OS Independent
Classifier: Programming Language :: Python :: 3
Classifier: Programming Language :: Python :: 3.9
Classifier: Programming Language :: Python :: 3.10
Classifier: Programming Language :: Python :: 3.11
Classifier: Programming Language :: Python :: 3.12
Classifier: Topic :: Software Development :: Libraries :: Python Modules
Classifier: Typing :: Typed
Requires-Python: >=3.9
Requires-Dist: httpx>=0.25.0
Requires-Dist: pydantic>=2.0.0
Provides-Extra: all
Requires-Dist: websockets>=14.0; extra == 'all'
Provides-Extra: dev
Requires-Dist: mypy>=1.9.0; extra == 'dev'
Requires-Dist: pytest-asyncio>=0.23.0; extra == 'dev'
Requires-Dist: pytest-cov>=4.0.0; extra == 'dev'
Requires-Dist: pytest>=8.0.0; extra == 'dev'
Requires-Dist: ruff>=0.4.0; extra == 'dev'
Provides-Extra: websocket
Requires-Dist: websockets>=14.0; extra == 'websocket'
